pysdtoken/__init__.py
pysdtoken/_sdauto.py
pysdtoken/pysdtoken.py
pysdtoken-1.0.0.dist-info/LICENSE
pysdtoken-1.0.0.dist-info/METADATA
pysdtoken-1.0.0.dist-info/WHEEL
pysdtoken-1.0.0.dist-info/top_level.txt
pysdtoken-1.0.0.dist-info/RECORD
