Metadata-Version: 2.1
Name: pysdtoken
Version: 1.0.0
Summary: Pythonic wrapper for the RSA sdauto32.dll soft token service
Home-page: https://github.com/XanaDublaKublaConch/pysdtoken/
Author: XanaDublaKublaConch
Author-email: XanaDublaKublaConch@styrophobia.org
License: UNKNOWN
Platform: UNKNOWN
Classifier: Programming Language :: Python :: 3
Classifier: License :: OSI Approved :: MIT License
Classifier: Operating System :: OS Independent
Classifier: Development Status :: 5 - Production/Stable
Requires-Python: >=3.7
Requires-Dist: pywin32-ctypes
